ShishangZuiJiandanDeIntellijIdeaJiaocheng/README.md
ShishangZuiJiandanDeIntellijIdeaJiaocheng/__init__.py
ShishangZuiJiandanDeIntellijIdeaJiaocheng/__main__.py
ShishangZuiJiandanDeIntellijIdeaJiaocheng/file.epub
ShishangZuiJiandanDeIntellijIdeaJiaocheng/index.html
ShishangZuiJiandanDeIntellijIdeaJiaocheng/css/__init__.py
ShishangZuiJiandanDeIntellijIdeaJiaocheng/css/annotations.css
ShishangZuiJiandanDeIntellijIdeaJiaocheng/css/main.css
ShishangZuiJiandanDeIntellijIdeaJiaocheng/css/normalize.css
ShishangZuiJiandanDeIntellijIdeaJiaocheng/css/popup.css
ShishangZuiJiandanDeIntellijIdeaJiaocheng/font/__init__.py
ShishangZuiJiandanDeIntellijIdeaJiaocheng/font/fontello.eot
ShishangZuiJiandanDeIntellijIdeaJiaocheng/font/fontello.svg
ShishangZuiJiandanDeIntellijIdeaJiaocheng/font/fontello.ttf
ShishangZuiJiandanDeIntellijIdeaJiaocheng/font/fontello.woff
ShishangZuiJiandanDeIntellijIdeaJiaocheng/img/__init__.py
ShishangZuiJiandanDeIntellijIdeaJiaocheng/img/annotator-glyph-sprite.png
ShishangZuiJiandanDeIntellijIdeaJiaocheng/img/annotator-icon-sprite.png
ShishangZuiJiandanDeIntellijIdeaJiaocheng/img/apple-touch-icon.png
ShishangZuiJiandanDeIntellijIdeaJiaocheng/img/cancelfullscreen.png
ShishangZuiJiandanDeIntellijIdeaJiaocheng/img/close.png
ShishangZuiJiandanDeIntellijIdeaJiaocheng/img/fullscreen.png
ShishangZuiJiandanDeIntellijIdeaJiaocheng/img/loader.gif
ShishangZuiJiandanDeIntellijIdeaJiaocheng/img/menu-icon.png
ShishangZuiJiandanDeIntellijIdeaJiaocheng/img/save.png
ShishangZuiJiandanDeIntellijIdeaJiaocheng/img/saved.png
ShishangZuiJiandanDeIntellijIdeaJiaocheng/img/settings-s.png
ShishangZuiJiandanDeIntellijIdeaJiaocheng/img/settings.png
ShishangZuiJiandanDeIntellijIdeaJiaocheng/img/star.png
ShishangZuiJiandanDeIntellijIdeaJiaocheng/js/__init__.py
ShishangZuiJiandanDeIntellijIdeaJiaocheng/js/epub.js
ShishangZuiJiandanDeIntellijIdeaJiaocheng/js/epub.min.js
ShishangZuiJiandanDeIntellijIdeaJiaocheng/js/epub.min.map
ShishangZuiJiandanDeIntellijIdeaJiaocheng/js/hooks.min.js
shishang_zui_jiandan_de_intellij_idea_jiaocheng-2024.3.3.0.dist-info/METADATA
shishang_zui_jiandan_de_intellij_idea_jiaocheng-2024.3.3.0.dist-info/WHEEL
shishang_zui_jiandan_de_intellij_idea_jiaocheng-2024.3.3.0.dist-info/entry_points.txt
shishang_zui_jiandan_de_intellij_idea_jiaocheng-2024.3.3.0.dist-info/top_level.txt
shishang_zui_jiandan_de_intellij_idea_jiaocheng-2024.3.3.0.dist-info/RECORD
